custom_password_generator/__init__.py
custom_password_generator-20220701.0.dist-info/LICENSE.md
custom_password_generator-20220701.0.dist-info/METADATA
custom_password_generator-20220701.0.dist-info/WHEEL
custom_password_generator-20220701.0.dist-info/top_level.txt
custom_password_generator-20220701.0.dist-info/RECORD
